pypi_rr_verify/__init__.py
pypi_rr_verify/main.py
pypi_rr_verify-0.2.0.dist-info/WHEEL
pypi_rr_verify-0.2.0.dist-info/METADATA
pypi_rr_verify-0.2.0.dist-info/RECORD
