Metadata-Version: 2.1
Name: pypi-rr-verify
Version: 0.2.0
Summary: Version tracking of published package.
License: MIT
Author: rroko
Author-email: roko.mislov@reversinglabs.com
Requires-Python: >=3.9,<4.0
Classifier: License :: OSI Approved :: MIT License
Classifier: Programming Language :: Python :: 3
Classifier: Programming Language :: Python :: 3.9
Classifier: Programming Language :: Python :: 3.10
Classifier: Programming Language :: Python :: 3.11
